featuretoolsOnSpark/__init__.py
featuretoolsOnSpark/column_types.py
featuretoolsOnSpark/dfs.py
featuretoolsOnSpark/relationship.py
featuretoolsOnSpark/table.py
featuretoolsOnSpark/tableset.py
featuretoolsOnSpark/util.py
featuretoolsOnSpark/version.py
featuretoolsOnSparkX-0.4.0.dist-info/LICENSE
featuretoolsOnSparkX-0.4.0.dist-info/METADATA
featuretoolsOnSparkX-0.4.0.dist-info/WHEEL
featuretoolsOnSparkX-0.4.0.dist-info/top_level.txt
featuretoolsOnSparkX-0.4.0.dist-info/RECORD
