Metadata-Version: 2.1
Name: featuretoolsOnSparkX
Version: 0.4.0
Summary: a bugfix version for raw repo
Home-page: https://github.com/tzbo/featuretoolsOnSpark
Author: giantcroc
Author-email: ringer0910@gmail.com
License: MIT
Keywords: feature engineering data science machine learning
Platform: UNKNOWN
Classifier: Development Status :: 2 - Pre-Alpha
Classifier: Intended Audience :: Developers
Classifier: Programming Language :: Python :: 2.7
Classifier: Programming Language :: Python :: 3
Classifier: Programming Language :: Python :: 3.5
Classifier: Programming Language :: Python :: 3.6
Classifier: Programming Language :: Python :: 3.7
Requires-Python: >=2.7, <4
License-File: LICENSE
Requires-Dist: numpy (>=1.13.3)
Requires-Dist: pandas (>=0.23.0)
Requires-Dist: future (>=0.16.0)
Requires-Dist: pyspark (>=2.3.2)
